HM1507_3GUI/HM1507_3GUI.py
HM1507_3GUI/__init__.py
HM1507_3GUI-0.4b0.dist-info/LICENSE
HM1507_3GUI-0.4b0.dist-info/METADATA
HM1507_3GUI-0.4b0.dist-info/WHEEL
HM1507_3GUI-0.4b0.dist-info/top_level.txt
HM1507_3GUI-0.4b0.dist-info/RECORD
