Metadata-Version: 2.1
Name: HM1507-3GUI
Version: 0.4b0
Summary: Module for saving data from the HAMEG HM1507-3 oscilloscope to the PC.
Home-page: https://github.com/pypa/sampleproject
Author: LukasFun, Jean-Claude Feltes
Author-email: lfreudenberg@uni-osnabrueck.de, jean-claude.feltes@education.lu
Project-URL: Bug Tracker, https://github.com/pypa/sampleproject/issues
Classifier: Programming Language :: Python :: 3
Classifier: License :: OSI Approved :: MIT License
Classifier: Operating System :: OS Independent
Requires-Python: >=3.6
License-File: LICENSE
